{"4950-000":["PT","4950-000","Mon\u00e7\u00e3o","Viana do Castelo","20","Mon\u00e7\u00e3o","1604","Mon\u00e7\u00e3o","","42.0789","-8.4808","4"],"4950-010":["PT","4950-010","Al\u00e9m","Viana do Castelo","20","Mon\u00e7\u00e3o","1604","Abedim","","41.9806","-8.5144","4"],"4950-020":["PT","4950-020","Aldeia","Viana do Castelo","20","Mon\u00e7\u00e3o","1604","Anh\u00f5es","","41.9908","-8.4287","4"],"4950-030":["PT","4950-030","Varziela","Viana do Castelo","20","Mon\u00e7\u00e3o","1604","Badim","","42.0566","-8.3583","4"],"4950-040":["PT","4950-040","Quinta do Padreiro","Viana do Castelo","20","Mon\u00e7\u00e3o","1604","Barbeita","","41.9954","-8.473","3"],"4950-041":["PT","4950-041","Abe\u00e7\u00e3o","Viana do Castelo","20","Mon\u00e7\u00e3o","1604","Barbeita","","42.0663","-8.4169","4"],"4950-042":["PT","4950-042","Ara\u00fajo","Viana do Castelo","20","Mon\u00e7\u00e3o","1604","Barbeita","","42.0647","-8.4101","4"],"4950-043":["PT","4950-043","Bairro Alto","Viana do Castelo","20","Mon\u00e7\u00e3o","1604","Barbeita","","42.0387","-8.4429","1"],"4950-044":["PT","4950-044","Bogadela","Viana do Castelo","20","Mon\u00e7\u00e3o","1604","Barbeita","","42.0387","-8.4429","1"],"4950-045":["PT","4950-045","Cabo","Viana do Castelo","20","Mon\u00e7\u00e3o","1604","Barbeita","","42.0635","-8.403","4"],"4950-046":["PT","4950-046","Cortinha","Viana do Castelo","20","Mon\u00e7\u00e3o","1604","Barbeita","","42.0387","-8.4429","1"],"4950-047":["PT","4950-047","Forte","Viana do Castelo","20","Mon\u00e7\u00e3o","1604","Barbeita","","42.0387","-8.4429","1"],"4950-048":["PT","4950-048","Lopes","Viana do Castelo","20","Mon\u00e7\u00e3o","1604","Barbeita","","42.0387","-8.4429","1"],"4950-049":["PT","4950-049","Macau","Viana do Castelo","20","Mon\u00e7\u00e3o","1604","Barbeita","","42.0387","-8.4429","1"],"4950-050":["PT","4950-050","Merim","Viana do Castelo","20","Mon\u00e7\u00e3o","1604","Barbeita","","42.0462","-8.4004","4"],"4950-051":["PT","4950-051","Padreiro","Viana do Castelo","20","Mon\u00e7\u00e3o","1604","Barbeita","","42.0635","-8.403","4"],"4950-052":["PT","4950-052","Ponte do Mouro","Viana do Castelo","20","Mon\u00e7\u00e3o","1604","Barbeita","","42.0755","-8.3947","4"],"4950-053":["PT","4950-053","Quartas","Viana do Castelo","20","Mon\u00e7\u00e3o","1604","Barbeita","","42.0635","-8.403","4"],"4950-054":["PT","4950-054","Santiago","Viana do Castelo","20","Mon\u00e7\u00e3o","1604","Barbeita","","42.0635","-8.403","4"],"4950-055":["PT","4950-055","Seixegal","Viana do Castelo","20","Mon\u00e7\u00e3o","1604","Barbeita","","41.9535","-8.4381","1"],"4950-056":["PT","4950-056","Souto","Viana do Castelo","20","Mon\u00e7\u00e3o","1604","Barbeita","","42.0635","-8.403","4"],"4950-057":["PT","4950-057","Tarendo","Viana do Castelo","20","Mon\u00e7\u00e3o","1604","Barbeita","","41.9535","-8.4381","1"],"4950-058":["PT","4950-058","Tola","Viana do Castelo","20","Mon\u00e7\u00e3o","1604","Barbeita","","41.9535","-8.4381","1"],"4950-059":["PT","4950-059","Veiga","Viana do Castelo","20","Mon\u00e7\u00e3o","1604","Barbeita","","42.0635","-8.403","4"],"4950-060":["PT","4950-060","Arroteia","Viana do Castelo","20","Mon\u00e7\u00e3o","1604","Barbeita","","42.029","-8.553","1"],"4950-061":["PT","4950-061","Cartas","Viana do Castelo","20","Mon\u00e7\u00e3o","1604","Barbeita","","42.029","-8.553","1"],"4950-062":["PT","4950-062","Crasto","Viana do Castelo","20","Mon\u00e7\u00e3o","1604","Barbeita","","42.0635","-8.403","4"],"4950-063":["PT","4950-063","Perdigueira","Viana do Castelo","20","Mon\u00e7\u00e3o","1604","Barbeita","","42.029","-8.553","1"],"4950-064":["PT","4950-064","Quinta de Miranques","Viana do Castelo","20","Mon\u00e7\u00e3o","1604","Barbeita","","42.029","-8.553","1"],"4950-070":["PT","4950-070","Cruz","Viana do Castelo","20","Mon\u00e7\u00e3o","1604","Barro\u00e7as E Taias","","42.0339","-8.4509","3"],"4950-080":["PT","4950-080","Santa Eug\u00e9nia","Viana do Castelo","20","Mon\u00e7\u00e3o","1604","Bela","","42.0507","-8.3916","3"],"4950-081":["PT","4950-081","Poldeiro","Viana do Castelo","20","Mon\u00e7\u00e3o","1604","Bela","","41.9458","-8.376","3"],"4950-082":["PT","4950-082","Barbeitos","Viana do Castelo","20","Mon\u00e7\u00e3o","1604","Bela","","42.0659","-8.4278","4"],"4950-083":["PT","4950-083","Burgo","Viana do Castelo","20","Mon\u00e7\u00e3o","1604","Bela","","42.0042","-8.4246","1"],"4950-084":["PT","4950-084","Cabo","Viana do Castelo","20","Mon\u00e7\u00e3o","1604","Bela","","42.0716","-8.4414","4"],"4950-085":["PT","4950-085","Costa","Viana do Castelo","20","Mon\u00e7\u00e3o","1604","Bela","","42.0659","-8.4278","4"],"4950-086":["PT","4950-086","Cruzeiro","Viana do Castelo","20","Mon\u00e7\u00e3o","1604","Bela","","42.0659","-8.4278","4"],"4950-087":["PT","4950-087","Devesa","Viana do Castelo","20","Mon\u00e7\u00e3o","1604","Bela","","42.0659","-8.4278","4"],"4950-088":["PT","4950-088","Fonte","Viana do Castelo","20","Mon\u00e7\u00e3o","1604","Bela","","42.0659","-8.4278","4"],"4950-089":["PT","4950-089","Giesteira","Viana do Castelo","20","Mon\u00e7\u00e3o","1604","Bela","","42.0705","-8.4405","4"],"4950-090":["PT","4950-090","Laginha","Viana do Castelo","20","Mon\u00e7\u00e3o","1604","Bela","","42.0677","-8.4347","1"],"4950-091":["PT","4950-091","Marco","Viana do Castelo","20","Mon\u00e7\u00e3o","1604","Bela","","42.0627","-8.4308","4"],"4950-092":["PT","4950-092","Mato","Viana do Castelo","20","Mon\u00e7\u00e3o","1604","Bela","","42.0659","-8.4278","1"],"4950-093":["PT","4950-093","Pereirinha","Viana do Castelo","20","Mon\u00e7\u00e3o","1604","Bela","","42.0677","-8.4347","1"],"4950-094":["PT","4950-094","Requeijo","Viana do Castelo","20","Mon\u00e7\u00e3o","1604","Bela","","42.0677","-8.4347","1"],"4950-095":["PT","4950-095","S\u00e3o Bento","Viana do Castelo","20","Mon\u00e7\u00e3o","1604","Bela","","42.0727","-8.4386","4"],"4950-096":["PT","4950-096","Telheira","Viana do Castelo","20","Mon\u00e7\u00e3o","1604","Bela","","42.0677","-8.4347","1"],"4950-100":["PT","4950-100","Terranova","Viana do Castelo","20","Mon\u00e7\u00e3o","1604","Cambeses Mnc","","41.9572","-8.5489","3"],"4950-101":["PT","4950-101","Carregal","Viana do Castelo","20","Mon\u00e7\u00e3o","1604","Cambeses Mnc","","41.965","-8.5324","1"],"4950-102":["PT","4950-102","Casa Nova","Viana do Castelo","20","Mon\u00e7\u00e3o","1604","Cambeses Mnc","","41.8667","-8.4667","4"],"4950-103":["PT","4950-103","Lagiela","Viana do Castelo","20","Mon\u00e7\u00e3o","1604","Cambeses Mnc","","41.965","-8.5324","1"],"4950-104":["PT","4950-104","Milagres","Viana do Castelo","20","Mon\u00e7\u00e3o","1604","Cambeses Mnc","","42.0468","-8.4686","4"],"4950-105":["PT","4950-105","Outeiro","Viana do Castelo","20","Mon\u00e7\u00e3o","1604","Cambeses Mnc","","42.0436","-8.5304","4"],"4950-106":["PT","4950-106","Sende","Viana do Castelo","20","Mon\u00e7\u00e3o","1604","Cambeses Mnc","","41.965","-8.5324","1"],"4950-120":["PT","4950-120","Sobreiro","Viana do Castelo","20","Mon\u00e7\u00e3o","1604","Ceiv\u00e3es","","42.0681","-8.382","4"],"4950-121":["PT","4950-121","Aspras","Viana do Castelo","20","Mon\u00e7\u00e3o","1604","Ceiv\u00e3es","","41.9812","-8.5024","1"],"4950-122":["PT","4950-122","Boucinha","Viana do Castelo","20","Mon\u00e7\u00e3o","1604","Ceiv\u00e3es","","41.9812","-8.5024","1"],"4950-123":["PT","4950-123","Cimo de Vila","Viana do Castelo","20","Mon\u00e7\u00e3o","1604","Ceiv\u00e3es","","41.9812","-8.5024","1"],"4950-124":["PT","4950-124","Coto","Viana do Castelo","20","Mon\u00e7\u00e3o","1604","Ceiv\u00e3es","","42.0681","-8.382","4"],"4950-125":["PT","4950-125","Cruzeiro","Viana do Castelo","20","Mon\u00e7\u00e3o","1604","Ceiv\u00e3es","","42.0681","-8.382","4"],"4950-126":["PT","4950-126","Devesas","Viana do Castelo","20","Mon\u00e7\u00e3o","1604","Ceiv\u00e3es","","42.0681","-8.382","4"],"4950-127":["PT","4950-127","Monjus\u00e3o","Viana do Castelo","20","Mon\u00e7\u00e3o","1604","Ceiv\u00e3es","","41.9812","-8.5024","1"],"4950-128":["PT","4950-128","Moucheira","Viana do Castelo","20","Mon\u00e7\u00e3o","1604","Ceiv\u00e3es","","42.0686","-8.3791","4"],"4950-129":["PT","4950-129","Pereiras","Viana do Castelo","20","Mon\u00e7\u00e3o","1604","Ceiv\u00e3es","","42.0681","-8.382","4"],"4950-130":["PT","4950-130","Ponte do Mouro","Viana do Castelo","20","Mon\u00e7\u00e3o","1604","Ceiv\u00e3es","","42.0755","-8.3947","4"],"4950-131":["PT","4950-131","Tejosas","Viana do Castelo","20","Mon\u00e7\u00e3o","1604","Ceiv\u00e3es","","42.055","-8.5246","1"],"4950-132":["PT","4950-132","Valinha","Viana do Castelo","20","Mon\u00e7\u00e3o","1604","Ceiv\u00e3es","","42.0681","-8.382","4"],"4950-135":["PT","4950-135","Lapela","Viana do Castelo","20","Mon\u00e7\u00e3o","1604","Lapela","","42.0559","-8.538","4"],"4950-136":["PT","4950-136","Lapela","Viana do Castelo","20","Mon\u00e7\u00e3o","1604","Lapela","","42.0559","-8.538","4"],"4950-137":["PT","4950-137","Lapela","Viana do Castelo","20","Mon\u00e7\u00e3o","1604","Lapela","","42.0559","-8.538","4"],"4950-138":["PT","4950-138","Lapela","Viana do Castelo","20","Mon\u00e7\u00e3o","1604","Lapela","","42.0559","-8.538","4"],"4950-139":["PT","4950-139","Lapela","Viana do Castelo","20","Mon\u00e7\u00e3o","1604","Lapela","","42.0559","-8.538","4"],"4950-140":["PT","4950-140","Lapela","Viana do Castelo","20","Mon\u00e7\u00e3o","1604","Lapela","","42.0559","-8.538","4"],"4950-141":["PT","4950-141","Lapela","Viana do Castelo","20","Mon\u00e7\u00e3o","1604","Lapela","","42.0559","-8.538","4"],"4950-142":["PT","4950-142","Lapela","Viana do Castelo","20","Mon\u00e7\u00e3o","1604","Lapela","","42.0559","-8.538","4"],"4950-143":["PT","4950-143","Lapela","Viana do Castelo","20","Mon\u00e7\u00e3o","1604","Lapela","","42.0559","-8.538","4"],"4950-144":["PT","4950-144","Lapela","Viana do Castelo","20","Mon\u00e7\u00e3o","1604","Lapela","","42.0559","-8.538","4"],"4950-145":["PT","4950-145","Lapela","Viana do Castelo","20","Mon\u00e7\u00e3o","1604","Lapela","","42.0559","-8.538","4"],"4950-146":["PT","4950-146","Lapela","Viana do Castelo","20","Mon\u00e7\u00e3o","1604","Lapela","","42.0559","-8.538","4"],"4950-147":["PT","4950-147","Lapela","Viana do Castelo","20","Mon\u00e7\u00e3o","1604","Lapela","","42.0559","-8.538","4"],"4950-148":["PT","4950-148","Lapela","Viana do Castelo","20","Mon\u00e7\u00e3o","1604","Lapela","","42.0559","-8.538","4"],"4950-149":["PT","4950-149","Lapela","Viana do Castelo","20","Mon\u00e7\u00e3o","1604","Lapela","","42.0559","-8.538","4"],"4950-150":["PT","4950-150","Lapela","Viana do Castelo","20","Mon\u00e7\u00e3o","1604","Lapela","","42.0559","-8.538","4"],"4950-170":["PT","4950-170","Outeiro","Viana do Castelo","20","Mon\u00e7\u00e3o","1604","Lara","","42.0405","-8.5283","4"],"4950-198":["PT","4950-198","Porto","Viana do Castelo","20","Mon\u00e7\u00e3o","1604","Longos Vales","","42.0453","-8.4348","4"],"4950-199":["PT","4950-199","Porqueira","Viana do Castelo","20","Mon\u00e7\u00e3o","1604","Longos Vales","","42.0463","-8.4105","4"],"4950-200":["PT","4950-200","Santo Amaro","Viana do Castelo","20","Mon\u00e7\u00e3o","1604","Longos Vales","","42.0453","-8.4348","4"],"4950-201":["PT","4950-201","Bou\u00e7a","Viana do Castelo","20","Mon\u00e7\u00e3o","1604","Longos Vales","","42.0453","-8.4348","4"],"4950-202":["PT","4950-202","Carvalhas","Viana do Castelo","20","Mon\u00e7\u00e3o","1604","Longos Vales","","42.0075","-8.423","1"],"4950-203":["PT","4950-203","Castelo","Viana do Castelo","20","Mon\u00e7\u00e3o","1604","Longos Vales","","42.05","-8.4333","4"],"4950-204":["PT","4950-204","Cesto","Viana do Castelo","20","Mon\u00e7\u00e3o","1604","Longos Vales","","42.0564","-8.445","4"],"4950-205":["PT","4950-205","Corgo","Viana do Castelo","20","Mon\u00e7\u00e3o","1604","Longos Vales","","42.0573","-8.4504","4"],"4950-206":["PT","4950-206","Costa","Viana do Castelo","20","Mon\u00e7\u00e3o","1604","Longos Vales","","42.0453","-8.4348","4"],"4950-207":["PT","4950-207","Guimil","Viana do Castelo","20","Mon\u00e7\u00e3o","1604","Longos Vales","","42.0414","-8.4201","4"],"4950-208":["PT","4950-208","Lavandeira","Viana do Castelo","20","Mon\u00e7\u00e3o","1604","Longos Vales","","42.0453","-8.4348","4"],"4950-209":["PT","4950-209","Moul\u00e3es","Viana do Castelo","20","Mon\u00e7\u00e3o","1604","Longos Vales","","42.0075","-8.423","1"],"4950-210":["PT","4950-210","Nogueira","Viana do Castelo","20","Mon\u00e7\u00e3o","1604","Longos Vales","","42.0453","-8.4348","4"],"4950-211":["PT","4950-211","Outeiro","Viana do Castelo","20","Mon\u00e7\u00e3o","1604","Longos Vales","","42.0351","-8.4383","4"],"4950-212":["PT","4950-212","Paradela de Baixo","Viana do Castelo","20","Mon\u00e7\u00e3o","1604","Longos Vales","","42.0186","-8.4397","1"],"4950-213":["PT","4950-213","Paradela de Cima","Viana do Castelo","20","Mon\u00e7\u00e3o","1604","Longos Vales","","42.0186","-8.4397","1"],"4950-214":["PT","4950-214","Reguengo de Baixo","Viana do Castelo","20","Mon\u00e7\u00e3o","1604","Longos Vales","","42.0186","-8.4397","1"],"4950-215":["PT","4950-215","Reguengo de Cima","Viana do Castelo","20","Mon\u00e7\u00e3o","1604","Longos Vales","","42.0186","-8.4397","1"],"4950-216":["PT","4950-216","Samar\u00e3o","Viana do Castelo","20","Mon\u00e7\u00e3o","1604","Longos Vales","","42.0488","-8.4584","4"],"4950-217":["PT","4950-217","Santa Tecla","Viana do Castelo","20","Mon\u00e7\u00e3o","1604","Longos Vales","","42.0331","-8.4373","4"],"4950-218":["PT","4950-218","Serzedo","Viana do Castelo","20","Mon\u00e7\u00e3o","1604","Longos Vales","","42.0186","-8.4397","1"],"4950-219":["PT","4950-219","Souto Fiscal","Viana do Castelo","20","Mon\u00e7\u00e3o","1604","Longos Vales","","42.0427","-8.4353","4"],"4950-220":["PT","4950-220","Valverde","Viana do Castelo","20","Mon\u00e7\u00e3o","1604","Longos Vales","","42.0453","-8.4348","1"],"4950-221":["PT","4950-221","V\u00e1rzea","Viana do Castelo","20","Mon\u00e7\u00e3o","1604","Longos Vales","","42.0453","-8.4348","4"],"4950-222":["PT","4950-222","Velhas","Viana do Castelo","20","Mon\u00e7\u00e3o","1604","Longos Vales","","42.0759","-8.3679","1"],"4950-223":["PT","4950-223","Vidal","Viana do Castelo","20","Mon\u00e7\u00e3o","1604","Longos Vales","","42.05","-8.45","4"],"4950-250":["PT","4950-250","Porto","Viana do Castelo","20","Mon\u00e7\u00e3o","1604","Lordelo Mnc","","42.0213","-8.4522","4"],"4950-270":["PT","4950-270","Formigueiro","Viana do Castelo","20","Mon\u00e7\u00e3o","1604","Luzio","","42.0253","-8.5108","3"],"4950-271":["PT","4950-271","Pedreiras","Viana do Castelo","20","Mon\u00e7\u00e3o","1604","Mazedo","","42.0553","-8.4919","4"],"4950-272":["PT","4950-272","Gandra","Viana do Castelo","20","Mon\u00e7\u00e3o","1604","Mazedo","","42.0553","-8.4919","4"],"4950-273":["PT","4950-273","Mazedo","Viana do Castelo","20","Mon\u00e7\u00e3o","1604","Mazedo","","42.0585","-8.4945","4"],"4950-275":["PT","4950-275","Mazedo","Viana do Castelo","20","Mon\u00e7\u00e3o","1604","Mazedo","","42.0585","-8.4945","4"],"4950-276":["PT","4950-276","Mazedo","Viana do Castelo","20","Mon\u00e7\u00e3o","1604","Mazedo","","42.0585","-8.4945","4"],"4950-277":["PT","4950-277","Barreiras","Viana do Castelo","20","Mon\u00e7\u00e3o","1604","Mazedo","","42.0394","-8.5166","1"],"4950-278":["PT","4950-278","Mazedo","Viana do Castelo","20","Mon\u00e7\u00e3o","1604","Mazedo","","42.0585","-8.4945","4"],"4950-279":["PT","4950-279","Cruzes","Viana do Castelo","20","Mon\u00e7\u00e3o","1604","Mazedo","","42.0394","-8.5166","1"],"4950-280":["PT","4950-280","Mazedo","Viana do Castelo","20","Mon\u00e7\u00e3o","1604","Mazedo","","42.0585","-8.4945","4"],"4950-281":["PT","4950-281","Agrelo","Viana do Castelo","20","Mon\u00e7\u00e3o","1604","Mazedo","","42.0553","-8.4919","1"],"4950-282":["PT","4950-282","Antoinha","Viana do Castelo","20","Mon\u00e7\u00e3o","1604","Mazedo","","42.061","-8.4914","4"],"4950-283":["PT","4950-283","Boavista","Viana do Castelo","20","Mon\u00e7\u00e3o","1604","Mazedo","","42.0728","-8.4891","4"],"4950-284":["PT","4950-284","Breia","Viana do Castelo","20","Mon\u00e7\u00e3o","1604","Mazedo","","42.0553","-8.4919","4"],"4950-285":["PT","4950-285","Calv\u00e1rio","Viana do Castelo","20","Mon\u00e7\u00e3o","1604","Mazedo","","42.0553","-8.4919","4"],"4950-286":["PT","4950-286","Carrazedo","Viana do Castelo","20","Mon\u00e7\u00e3o","1604","Mazedo","","42.0287","-8.5055","1"],"4950-287":["PT","4950-287","Veiga","Viana do Castelo","20","Mon\u00e7\u00e3o","1604","Mazedo","","42.0553","-8.4919","4"],"4950-288":["PT","4950-288","Estrada","Viana do Castelo","20","Mon\u00e7\u00e3o","1604","Mazedo","","42.05","-8.4833","4"],"4950-289":["PT","4950-289","Mazedo","Viana do Castelo","20","Mon\u00e7\u00e3o","1604","Mazedo","","42.0585","-8.4945","4"],"4950-290":["PT","4950-290","Mazedo","Viana do Castelo","20","Mon\u00e7\u00e3o","1604","Mazedo","","42.0585","-8.4945","4"],"4950-291":["PT","4950-291","Mazedo","Viana do Castelo","20","Mon\u00e7\u00e3o","1604","Mazedo","","42.0585","-8.4945","4"],"4950-292":["PT","4950-292","Pegadeira","Viana do Castelo","20","Mon\u00e7\u00e3o","1604","Mazedo","","42.0323","-8.5132","1"],"4950-293":["PT","4950-293","Pomar","Viana do Castelo","20","Mon\u00e7\u00e3o","1604","Mazedo","","42.0458","-8.4841","4"],"4950-294":["PT","4950-294","Igreja","Viana do Castelo","20","Mon\u00e7\u00e3o","1604","Mazedo","","42.0553","-8.4919","4"],"4950-295":["PT","4950-295","Regueiro","Viana do Castelo","20","Mon\u00e7\u00e3o","1604","Mazedo","","42.0323","-8.5132","1"],"4950-296":["PT","4950-296","Casas Novas","Viana do Castelo","20","Mon\u00e7\u00e3o","1604","Mazedo","","42.05","-8.5","3"],"4950-297":["PT","4950-297","Sobreiro","Viana do Castelo","20","Mon\u00e7\u00e3o","1604","Mazedo","","42.0553","-8.4919","4"],"4950-298":["PT","4950-298","Gandra","Viana do Castelo","20","Mon\u00e7\u00e3o","1604","Mazedo","","42.0553","-8.4919","4"],"4950-300":["PT","4950-300","Eirados","Viana do Castelo","20","Mon\u00e7\u00e3o","1604","Mazedo","","42.0585","-8.4945","1"],"4950-301":["PT","4950-301","Mazedo","Viana do Castelo","20","Mon\u00e7\u00e3o","1604","Mazedo","","42.0585","-8.4945","4"],"4950-302":["PT","4950-302","Mazedo","Viana do Castelo","20","Mon\u00e7\u00e3o","1604","Mazedo","","42.0585","-8.4945","4"],"4950-310":["PT","4950-310","Reguenga","Viana do Castelo","20","Mon\u00e7\u00e3o","1604","Merufe","","42.0352","-8.4612","3"],"4950-311":["PT","4950-311","Portela do Alvite","Viana do Castelo","20","Mon\u00e7\u00e3o","1604","Merufe","","42.0261","-8.4514","3"],"4950-312":["PT","4950-312","Azevedo","Viana do Castelo","20","Mon\u00e7\u00e3o","1604","Merufe","","42.0229","-8.4033","4"],"4950-313":["PT","4950-313","Campo Longo","Viana do Castelo","20","Mon\u00e7\u00e3o","1604","Merufe","","42.0035","-8.4134","1"],"4950-314":["PT","4950-314","Fundevila","Viana do Castelo","20","Mon\u00e7\u00e3o","1604","Merufe","","42.0035","-8.4134","1"],"4950-315":["PT","4950-315","Granja de Baixo","Viana do Castelo","20","Mon\u00e7\u00e3o","1604","Merufe","","42.0038","-8.3733","4"],"4950-316":["PT","4950-316","Granja de Cima","Viana do Castelo","20","Mon\u00e7\u00e3o","1604","Merufe","","41.9997","-8.3669","4"],"4950-317":["PT","4950-317","Lavandeira","Viana do Castelo","20","Mon\u00e7\u00e3o","1604","Merufe","","41.9891","-8.3698","4"],"4950-318":["PT","4950-318","Mosteiro","Viana do Castelo","20","Mon\u00e7\u00e3o","1604","Merufe","","42.007","-8.3952","4"],"4950-319":["PT","4950-319","Pereira","Viana do Castelo","20","Mon\u00e7\u00e3o","1604","Merufe","","42.007","-8.3952","4"],"4950-320":["PT","4950-320","Parada","Viana do Castelo","20","Mon\u00e7\u00e3o","1604","Merufe","","42.007","-8.3952","4"],"4950-322":["PT","4950-322","Pias","Viana do Castelo","20","Mon\u00e7\u00e3o","1604","Merufe","","42.0313","-8.3859","4"],"4950-323":["PT","4950-323","Pica","Viana do Castelo","20","Mon\u00e7\u00e3o","1604","Merufe","","42.0338","-8.3954","4"],"4950-324":["PT","4950-324","Pretos","Viana do Castelo","20","Mon\u00e7\u00e3o","1604","Merufe","","42.0383","-8.3973","4"],"4950-325":["PT","4950-325","Quinteiro","Viana do Castelo","20","Mon\u00e7\u00e3o","1604","Merufe","","42.0382","-8.4064","4"],"4950-326":["PT","4950-326","Real","Viana do Castelo","20","Mon\u00e7\u00e3o","1604","Merufe","","42.007","-8.3952","4"],"4950-327":["PT","4950-327","Ribeiro","Viana do Castelo","20","Mon\u00e7\u00e3o","1604","Merufe","","42.0277","-8.4035","4"],"4950-328":["PT","4950-328","Salgueiro","Viana do Castelo","20","Mon\u00e7\u00e3o","1604","Merufe","","42.0367","-8.4182","1"],"4950-329":["PT","4950-329","Santo Andr\u00e9","Viana do Castelo","20","Mon\u00e7\u00e3o","1604","Merufe","","42.0297","-8.4105","4"],"4950-330":["PT","4950-330","Senra","Viana do Castelo","20","Mon\u00e7\u00e3o","1604","Merufe","","42.007","-8.3952","4"],"4950-331":["PT","4950-331","Sernades","Viana do Castelo","20","Mon\u00e7\u00e3o","1604","Merufe","","41.9488","-8.4345","1"],"4950-332":["PT","4950-332","Lages","Viana do Castelo","20","Mon\u00e7\u00e3o","1604","Merufe","","41.9821","-8.4486","3"],"4950-350":["PT","4950-350","S\u00e3o Miguel","Viana do Castelo","20","Mon\u00e7\u00e3o","1604","Messeg\u00e3es","","42.0218","-8.465","3"],"4950-351":["PT","4950-351","Cachada","Viana do Castelo","20","Mon\u00e7\u00e3o","1604","Messeg\u00e3es","","42.081","-8.3674","4"],"4950-352":["PT","4950-352","Ch\u00e3o","Viana do Castelo","20","Mon\u00e7\u00e3o","1604","Messeg\u00e3es","","42.0806","-8.3682","1"],"4950-353":["PT","4950-353","Cova","Viana do Castelo","20","Mon\u00e7\u00e3o","1604","Messeg\u00e3es","","42.0806","-8.3682","1"],"4950-354":["PT","4950-354","Cruzeiro","Viana do Castelo","20","Mon\u00e7\u00e3o","1604","Messeg\u00e3es","","42.0806","-8.3682","4"],"4950-355":["PT","4950-355","Pa\u00e7o","Viana do Castelo","20","Mon\u00e7\u00e3o","1604","Messeg\u00e3es","","42.0725","-8.3675","4"],"4950-356":["PT","4950-356","Pereiro","Viana do Castelo","20","Mon\u00e7\u00e3o","1604","Messeg\u00e3es","","42.0806","-8.3682","4"],"4950-357":["PT","4950-357","Senra","Viana do Castelo","20","Mon\u00e7\u00e3o","1604","Messeg\u00e3es","","42.0806","-8.3682","4"],"4950-358":["PT","4950-358","Vila","Viana do Castelo","20","Mon\u00e7\u00e3o","1604","Messeg\u00e3es","","42.0129","-8.4423","1"],"4950-359":["PT","4950-359","Angueiro","Viana do Castelo","20","Mon\u00e7\u00e3o","1604","Messeg\u00e3es","","42.0129","-8.4423","1"],"4950-400":["PT","4950-400","Mon\u00e7\u00e3o","Viana do Castelo","20","Mon\u00e7\u00e3o","1604","Mon\u00e7\u00e3o","","42.0789","-8.4808","4"],"4950-402":["PT","4950-402","Bairro Fundo Fomento Habita\u00e7\u00e3o","Viana do Castelo","20","Mon\u00e7\u00e3o","1604","Mon\u00e7\u00e3o","","42.0368","-8.4608","1"],"4950-404":["PT","4950-404","Barreiras","Viana do Castelo","20","Mon\u00e7\u00e3o","1604","Mon\u00e7\u00e3o","","42.0368","-8.4608","1"],"4950-405":["PT","4950-405","Caldas","Viana do Castelo","20","Mon\u00e7\u00e3o","1604","Mon\u00e7\u00e3o","","42.0784","-8.4741","4"],"4950-406":["PT","4950-406","Ferreiros","Viana do Castelo","20","Mon\u00e7\u00e3o","1604","Mon\u00e7\u00e3o","","42.0715","-8.4786","4"],"4950-407":["PT","4950-407","Fora de Portas","Viana do Castelo","20","Mon\u00e7\u00e3o","1604","Mon\u00e7\u00e3o","","42.0368","-8.4608","1"],"4950-408":["PT","4950-408","Forte","Viana do Castelo","20","Mon\u00e7\u00e3o","1604","Mon\u00e7\u00e3o","","42.0368","-8.4608","1"],"4950-409":["PT","4950-409","Mon\u00e7\u00e3o","Viana do Castelo","20","Mon\u00e7\u00e3o","1604","Mon\u00e7\u00e3o","","42.0789","-8.4808","4"],"4950-410":["PT","4950-410","Mon\u00e7\u00e3o","Viana do Castelo","20","Mon\u00e7\u00e3o","1604","Mon\u00e7\u00e3o","","42.0789","-8.4808","4"],"4950-411":["PT","4950-411","Mon\u00e7\u00e3o","Viana do Castelo","20","Mon\u00e7\u00e3o","1604","Mon\u00e7\u00e3o","","42.0789","-8.4808","4"],"4950-412":["PT","4950-412","Mon\u00e7\u00e3o","Viana do Castelo","20","Mon\u00e7\u00e3o","1604","Mon\u00e7\u00e3o","","42.0789","-8.4808","4"],"4950-413":["PT","4950-413","Mon\u00e7\u00e3o","Viana do Castelo","20","Mon\u00e7\u00e3o","1604","Mon\u00e7\u00e3o","","42.0789","-8.4808","4"],"4950-414":["PT","4950-414","Mon\u00e7\u00e3o","Viana do Castelo","20","Mon\u00e7\u00e3o","1604","Mon\u00e7\u00e3o","","42.0789","-8.4808","4"],"4950-415":["PT","4950-415","Mon\u00e7\u00e3o","Viana do Castelo","20","Mon\u00e7\u00e3o","1604","Mon\u00e7\u00e3o","","42.0789","-8.4808","4"],"4950-416":["PT","4950-416","Mon\u00e7\u00e3o","Viana do Castelo","20","Mon\u00e7\u00e3o","1604","Mon\u00e7\u00e3o","","42.0789","-8.4808","4"],"4950-417":["PT","4950-417","Mon\u00e7\u00e3o","Viana do Castelo","20","Mon\u00e7\u00e3o","1604","Mon\u00e7\u00e3o","","42.0789","-8.4808","4"],"4950-418":["PT","4950-418","Mon\u00e7\u00e3o","Viana do Castelo","20","Mon\u00e7\u00e3o","1604","Mon\u00e7\u00e3o","","42.0789","-8.4808","4"],"4950-419":["PT","4950-419","Mon\u00e7\u00e3o","Viana do Castelo","20","Mon\u00e7\u00e3o","1604","Mon\u00e7\u00e3o","","42.0789","-8.4808","4"],"4950-420":["PT","4950-420","Mon\u00e7\u00e3o","Viana do Castelo","20","Mon\u00e7\u00e3o","1604","Mon\u00e7\u00e3o","","42.0789","-8.4808","4"],"4950-421":["PT","4950-421","Mon\u00e7\u00e3o","Viana do Castelo","20","Mon\u00e7\u00e3o","1604","Mon\u00e7\u00e3o","","42.0789","-8.4808","4"],"4950-422":["PT","4950-422","Mon\u00e7\u00e3o","Viana do Castelo","20","Mon\u00e7\u00e3o","1604","Mon\u00e7\u00e3o","","42.0789","-8.4808","4"],"4950-423":["PT","4950-423","Mon\u00e7\u00e3o","Viana do Castelo","20","Mon\u00e7\u00e3o","1604","Mon\u00e7\u00e3o","","42.0789","-8.4808","4"],"4950-424":["PT","4950-424","Mon\u00e7\u00e3o","Viana do Castelo","20","Mon\u00e7\u00e3o","1604","Mon\u00e7\u00e3o","","42.0789","-8.4808","4"],"4950-425":["PT","4950-425","Mazedo","Viana do Castelo","20","Mon\u00e7\u00e3o","1604","Mazedo","","42.0585","-8.4945","4"],"4950-426":["PT","4950-426","Mon\u00e7\u00e3o","Viana do Castelo","20","Mon\u00e7\u00e3o","1604","Mon\u00e7\u00e3o","","42.0789","-8.4808","4"],"4950-427":["PT","4950-427","Mon\u00e7\u00e3o","Viana do Castelo","20","Mon\u00e7\u00e3o","1604","Mon\u00e7\u00e3o","","42.0789","-8.4808","4"],"4950-428":["PT","4950-428","Mon\u00e7\u00e3o","Viana do Castelo","20","Mon\u00e7\u00e3o","1604","Mon\u00e7\u00e3o","","42.0789","-8.4808","4"],"4950-429":["PT","4950-429","Mon\u00e7\u00e3o","Viana do Castelo","20","Mon\u00e7\u00e3o","1604","Mon\u00e7\u00e3o","","42.0789","-8.4808","4"],"4950-430":["PT","4950-430","Mon\u00e7\u00e3o","Viana do Castelo","20","Mon\u00e7\u00e3o","1604","Mon\u00e7\u00e3o","","42.0789","-8.4808","4"],"4950-431":["PT","4950-431","Mon\u00e7\u00e3o","Viana do Castelo","20","Mon\u00e7\u00e3o","1604","Mon\u00e7\u00e3o","","42.0789","-8.4808","4"],"4950-432":["PT","4950-432","Mon\u00e7\u00e3o","Viana do Castelo","20","Mon\u00e7\u00e3o","1604","Mon\u00e7\u00e3o","","42.0789","-8.4808","4"],"4950-433":["PT","4950-433","Mon\u00e7\u00e3o","Viana do Castelo","20","Mon\u00e7\u00e3o","1604","Mon\u00e7\u00e3o","","42.0789","-8.4808","4"],"4950-436":["PT","4950-436","Mon\u00e7\u00e3o","Viana do Castelo","20","Mon\u00e7\u00e3o","1604","Mon\u00e7\u00e3o","","42.0789","-8.4808","4"],"4950-437":["PT","4950-437","Mon\u00e7\u00e3o","Viana do Castelo","20","Mon\u00e7\u00e3o","1604","Mon\u00e7\u00e3o","","42.0789","-8.4808","4"],"4950-438":["PT","4950-438","Mon\u00e7\u00e3o","Viana do Castelo","20","Mon\u00e7\u00e3o","1604","Mon\u00e7\u00e3o","","42.0789","-8.4808","4"],"4950-439":["PT","4950-439","Mon\u00e7\u00e3o","Viana do Castelo","20","Mon\u00e7\u00e3o","1604","Mon\u00e7\u00e3o","","42.0789","-8.4808","4"],"4950-440":["PT","4950-440","Mon\u00e7\u00e3o","Viana do Castelo","20","Mon\u00e7\u00e3o","1604","Mon\u00e7\u00e3o","","42.0789","-8.4808","4"],"4950-441":["PT","4950-441","Mon\u00e7\u00e3o","Viana do Castelo","20","Mon\u00e7\u00e3o","1604","Mon\u00e7\u00e3o","","42.0789","-8.4808","4"],"4950-442":["PT","4950-442","Mon\u00e7\u00e3o","Viana do Castelo","20","Mon\u00e7\u00e3o","1604","Mon\u00e7\u00e3o","","42.0789","-8.4808","4"],"4950-444":["PT","4950-444","Mon\u00e7\u00e3o","Viana do Castelo","20","Mon\u00e7\u00e3o","1604","Mon\u00e7\u00e3o","","42.0789","-8.4808","4"],"4950-445":["PT","4950-445","Mon\u00e7\u00e3o","Viana do Castelo","20","Mon\u00e7\u00e3o","1604","Mon\u00e7\u00e3o","","42.0789","-8.4808","4"],"4950-446":["PT","4950-446","Mon\u00e7\u00e3o","Viana do Castelo","20","Mon\u00e7\u00e3o","1604","Mon\u00e7\u00e3o","","42.0789","-8.4808","4"],"4950-447":["PT","4950-447","Mon\u00e7\u00e3o","Viana do Castelo","20","Mon\u00e7\u00e3o","1604","Mon\u00e7\u00e3o","","42.0789","-8.4808","4"],"4950-449":["PT","4950-449","Mon\u00e7\u00e3o","Viana do Castelo","20","Mon\u00e7\u00e3o","1604","Mon\u00e7\u00e3o","","42.0789","-8.4808","4"],"4950-452":["PT","4950-452","Mon\u00e7\u00e3o","Viana do Castelo","20","Mon\u00e7\u00e3o","1604","Mon\u00e7\u00e3o","","42.0789","-8.4808","4"],"4950-454":["PT","4950-454","Mon\u00e7\u00e3o","Viana do Castelo","20","Mon\u00e7\u00e3o","1604","Mon\u00e7\u00e3o","","42.0789","-8.4808","4"],"4950-455":["PT","4950-455","Mon\u00e7\u00e3o","Viana do Castelo","20","Mon\u00e7\u00e3o","1604","Mon\u00e7\u00e3o","","42.0789","-8.4808","4"],"4950-456":["PT","4950-456","Mon\u00e7\u00e3o","Viana do Castelo","20","Mon\u00e7\u00e3o","1604","Mon\u00e7\u00e3o","","42.0789","-8.4808","4"],"4950-457":["PT","4950-457","Mon\u00e7\u00e3o","Viana do Castelo","20","Mon\u00e7\u00e3o","1604","Mon\u00e7\u00e3o","","42.0789","-8.4808","4"],"4950-458":["PT","4950-458","Mon\u00e7\u00e3o","Viana do Castelo","20","Mon\u00e7\u00e3o","1604","Mon\u00e7\u00e3o","","42.0789","-8.4808","4"],"4950-463":["PT","4950-463","Mon\u00e7\u00e3o","Viana do Castelo","20","Mon\u00e7\u00e3o","1604","Mon\u00e7\u00e3o","","42.0789","-8.4808","4"],"4950-464":["PT","4950-464","Mon\u00e7\u00e3o","Viana do Castelo","20","Mon\u00e7\u00e3o","1604","Mon\u00e7\u00e3o","","42.0789","-8.4808","4"],"4950-465":["PT","4950-465","Mon\u00e7\u00e3o","Viana do Castelo","20","Mon\u00e7\u00e3o","1604","Mon\u00e7\u00e3o","","42.0789","-8.4808","4"],"4950-466":["PT","4950-466","Mon\u00e7\u00e3o","Viana do Castelo","20","Mon\u00e7\u00e3o","1604","Mon\u00e7\u00e3o","","42.0789","-8.4808","4"],"4950-467":["PT","4950-467","Mon\u00e7\u00e3o","Viana do Castelo","20","Mon\u00e7\u00e3o","1604","Mon\u00e7\u00e3o","","42.0789","-8.4808","4"],"4950-468":["PT","4950-468","Mon\u00e7\u00e3o","Viana do Castelo","20","Mon\u00e7\u00e3o","1604","Mon\u00e7\u00e3o","","42.0789","-8.4808","4"],"4950-469":["PT","4950-469","Mon\u00e7\u00e3o","Viana do Castelo","20","Mon\u00e7\u00e3o","1604","Mon\u00e7\u00e3o","","42.0789","-8.4808","4"],"4950-470":["PT","4950-470","Mon\u00e7\u00e3o","Viana do Castelo","20","Mon\u00e7\u00e3o","1604","Mon\u00e7\u00e3o","","42.0789","-8.4808","4"],"4950-471":["PT","4950-471","Mon\u00e7\u00e3o","Viana do Castelo","20","Mon\u00e7\u00e3o","1604","Mon\u00e7\u00e3o","","42.0789","-8.4808","4"],"4950-472":["PT","4950-472","Mon\u00e7\u00e3o","Viana do Castelo","20","Mon\u00e7\u00e3o","1604","Mon\u00e7\u00e3o","","42.0789","-8.4808","4"],"4950-473":["PT","4950-473","Mon\u00e7\u00e3o","Viana do Castelo","20","Mon\u00e7\u00e3o","1604","Mon\u00e7\u00e3o","","42.0789","-8.4808","4"],"4950-474":["PT","4950-474","Mon\u00e7\u00e3o","Viana do Castelo","20","Mon\u00e7\u00e3o","1604","Mon\u00e7\u00e3o","","42.0789","-8.4808","4"],"4950-478":["PT","4950-478","Mon\u00e7\u00e3o","Viana do Castelo","20","Mon\u00e7\u00e3o","1604","Mon\u00e7\u00e3o","","42.0789","-8.4808","4"],"4950-480":["PT","4950-480","Mon\u00e7\u00e3o","Viana do Castelo","20","Mon\u00e7\u00e3o","1604","Mon\u00e7\u00e3o","","42.0789","-8.4808","4"],"4950-482":["PT","4950-482","Mon\u00e7\u00e3o","Viana do Castelo","20","Mon\u00e7\u00e3o","1604","Mon\u00e7\u00e3o","","42.0789","-8.4808","4"],"4950-483":["PT","4950-483","Mon\u00e7\u00e3o","Viana do Castelo","20","Mon\u00e7\u00e3o","1604","Mon\u00e7\u00e3o","","42.0789","-8.4808","4"],"4950-484":["PT","4950-484","Mon\u00e7\u00e3o","Viana do Castelo","20","Mon\u00e7\u00e3o","1604","Mon\u00e7\u00e3o","","42.0789","-8.4808","4"],"4950-486":["PT","4950-486","Mon\u00e7\u00e3o","Viana do Castelo","20","Mon\u00e7\u00e3o","1604","Mon\u00e7\u00e3o","","42.0789","-8.4808","4"],"4950-487":["PT","4950-487","Mon\u00e7\u00e3o","Viana do Castelo","20","Mon\u00e7\u00e3o","1604","Mon\u00e7\u00e3o","","42.0789","-8.4808","4"],"4950-488":["PT","4950-488","Mon\u00e7\u00e3o","Viana do Castelo","20","Mon\u00e7\u00e3o","1604","Mon\u00e7\u00e3o","","42.0789","-8.4808","4"],"4950-489":["PT","4950-489","Mon\u00e7\u00e3o","Viana do Castelo","20","Mon\u00e7\u00e3o","1604","Mon\u00e7\u00e3o","","42.0789","-8.4808","4"],"4950-491":["PT","4950-491","Mon\u00e7\u00e3o","Viana do Castelo","20","Mon\u00e7\u00e3o","1604","Mon\u00e7\u00e3o","","42.0789","-8.4808","4"],"4950-492":["PT","4950-492","Mon\u00e7\u00e3o","Viana do Castelo","20","Mon\u00e7\u00e3o","1604","Mon\u00e7\u00e3o","","42.0789","-8.4808","4"],"4950-493":["PT","4950-493","Mon\u00e7\u00e3o","Viana do Castelo","20","Mon\u00e7\u00e3o","1604","Mon\u00e7\u00e3o","","42.0789","-8.4808","4"],"4950-494":["PT","4950-494","Mon\u00e7\u00e3o","Viana do Castelo","20","Mon\u00e7\u00e3o","1604","Mon\u00e7\u00e3o","","42.0789","-8.4808","4"],"4950-495":["PT","4950-495","Mon\u00e7\u00e3o","Viana do Castelo","20","Mon\u00e7\u00e3o","1604","Mon\u00e7\u00e3o","","42.0789","-8.4808","4"],"4950-497":["PT","4950-497","Mon\u00e7\u00e3o","Viana do Castelo","20","Mon\u00e7\u00e3o","1604","Mon\u00e7\u00e3o","","42.0789","-8.4808","4"],"4950-498":["PT","4950-498","Mon\u00e7\u00e3o","Viana do Castelo","20","Mon\u00e7\u00e3o","1604","Mon\u00e7\u00e3o","","42.0789","-8.4808","4"],"4950-500":["PT","4950-500","Mon\u00e7\u00e3o","Viana do Castelo","20","Mon\u00e7\u00e3o","1604","Mon\u00e7\u00e3o","","42.0789","-8.4808","4"],"4950-502":["PT","4950-502","Mon\u00e7\u00e3o","Viana do Castelo","20","Mon\u00e7\u00e3o","1604","Mon\u00e7\u00e3o","","42.0789","-8.4808","4"],"4950-505":["PT","4950-505","Mon\u00e7\u00e3o","Viana do Castelo","20","Mon\u00e7\u00e3o","1604","Mon\u00e7\u00e3o","","42.0789","-8.4808","4"],"4950-506":["PT","4950-506","Mon\u00e7\u00e3o","Viana do Castelo","20","Mon\u00e7\u00e3o","1604","Mon\u00e7\u00e3o","","42.0789","-8.4808","4"],"4950-508":["PT","4950-508","Mon\u00e7\u00e3o","Viana do Castelo","20","Mon\u00e7\u00e3o","1604","Mon\u00e7\u00e3o","","42.0789","-8.4808","4"],"4950-509":["PT","4950-509","Mon\u00e7\u00e3o","Viana do Castelo","20","Mon\u00e7\u00e3o","1604","Mon\u00e7\u00e3o","","42.0789","-8.4808","4"],"4950-510":["PT","4950-510","Mon\u00e7\u00e3o","Viana do Castelo","20","Mon\u00e7\u00e3o","1604","Mon\u00e7\u00e3o","","42.0789","-8.4808","4"],"4950-512":["PT","4950-512","Mon\u00e7\u00e3o","Viana do Castelo","20","Mon\u00e7\u00e3o","1604","Mon\u00e7\u00e3o","","42.0789","-8.4808","4"],"4950-513":["PT","4950-513","Mon\u00e7\u00e3o","Viana do Castelo","20","Mon\u00e7\u00e3o","1604","Mon\u00e7\u00e3o","","42.0789","-8.4808","4"],"4950-516":["PT","4950-516","Mon\u00e7\u00e3o","Viana do Castelo","20","Mon\u00e7\u00e3o","1604","Mon\u00e7\u00e3o","","42.0789","-8.4808","4"],"4950-517":["PT","4950-517","Mon\u00e7\u00e3o","Viana do Castelo","20","Mon\u00e7\u00e3o","1604","Mon\u00e7\u00e3o","","42.0789","-8.4808","4"],"4950-520":["PT","4950-520","Mon\u00e7\u00e3o","Viana do Castelo","20","Mon\u00e7\u00e3o","1604","Mon\u00e7\u00e3o","","42.0789","-8.4808","4"],"4950-521":["PT","4950-521","Pousa","Viana do Castelo","20","Mon\u00e7\u00e3o","1604","Mon\u00e7\u00e3o","","42.0715","-8.4786","4"],"4950-522":["PT","4950-522","Quinta da Barca","Viana do Castelo","20","Mon\u00e7\u00e3o","1604","Mon\u00e7\u00e3o","","42.0804","-8.4216","1"],"4950-523":["PT","4950-523","Quinta de Juste","Viana do Castelo","20","Mon\u00e7\u00e3o","1604","Mon\u00e7\u00e3o","","42.0804","-8.4216","1"],"4950-524":["PT","4950-524","Quinta de Rodas","Viana do Castelo","20","Mon\u00e7\u00e3o","1604","Mon\u00e7\u00e3o","","42.0804","-8.4216","1"],"4950-525":["PT","4950-525","Quinta de S\u00e3o Bento","Viana do Castelo","20","Mon\u00e7\u00e3o","1604","Mon\u00e7\u00e3o","","42.0804","-8.4216","1"],"4950-526":["PT","4950-526","Quinta do Garrido","Viana do Castelo","20","Mon\u00e7\u00e3o","1604","Mon\u00e7\u00e3o","","42.0804","-8.4216","1"],"4950-527":["PT","4950-527","Quinta dos Capuchos","Viana do Castelo","20","Mon\u00e7\u00e3o","1604","Mon\u00e7\u00e3o","","42.0804","-8.4216","1"],"4950-528":["PT","4950-528","Real","Viana do Castelo","20","Mon\u00e7\u00e3o","1604","Mon\u00e7\u00e3o","","42.0744","-8.4817","4"],"4950-529":["PT","4950-529","Rodas","Viana do Castelo","20","Mon\u00e7\u00e3o","1604","Mon\u00e7\u00e3o","","42.0645","-8.4772","4"],"4950-530":["PT","4950-530","S\u00e3o Pedro","Viana do Castelo","20","Mon\u00e7\u00e3o","1604","Mon\u00e7\u00e3o","","42.0715","-8.4786","1"],"4950-531":["PT","4950-531","Souto","Viana do Castelo","20","Mon\u00e7\u00e3o","1604","Mon\u00e7\u00e3o","","42.0715","-8.4786","4"],"4950-532":["PT","4950-532","Urzilh\u00e3o","Viana do Castelo","20","Mon\u00e7\u00e3o","1604","Mon\u00e7\u00e3o","","42.0671","-8.5015","1"],"4950-533":["PT","4950-533","Ventozelo","Viana do Castelo","20","Mon\u00e7\u00e3o","1604","Mon\u00e7\u00e3o","","42.0671","-8.5015","1"],"4950-534":["PT","4950-534","Mon\u00e7\u00e3o","Viana do Castelo","20","Mon\u00e7\u00e3o","1604","Mon\u00e7\u00e3o","","42.0789","-8.4808","4"],"4950-600":["PT","4950-600","Moreira","Viana do Castelo","20","Mon\u00e7\u00e3o","1604","Moreira Mnc","","42.0226","-8.4875","4"],"4950-601":["PT","4950-601","Moreira","Viana do Castelo","20","Mon\u00e7\u00e3o","1604","Moreira Mnc","","42.0226","-8.4875","4"],"4950-602":["PT","4950-602","Moreira","Viana do Castelo","20","Mon\u00e7\u00e3o","1604","Moreira Mnc","","42.0226","-8.4875","4"],"4950-603":["PT","4950-603","Moreira","Viana do Castelo","20","Mon\u00e7\u00e3o","1604","Moreira Mnc","","42.0226","-8.4875","4"],"4950-604":["PT","4950-604","Moreira","Viana do Castelo","20","Mon\u00e7\u00e3o","1604","Moreira Mnc","","42.0226","-8.4875","4"],"4950-605":["PT","4950-605","Moreira","Viana do Castelo","20","Mon\u00e7\u00e3o","1604","Moreira Mnc","","42.0226","-8.4875","4"],"4950-606":["PT","4950-606","Moreira","Viana do Castelo","20","Mon\u00e7\u00e3o","1604","Moreira Mnc","","42.0226","-8.4875","4"],"4950-607":["PT","4950-607","Moreira","Viana do Castelo","20","Mon\u00e7\u00e3o","1604","Moreira Mnc","","42.0226","-8.4875","4"],"4950-608":["PT","4950-608","Moreira","Viana do Castelo","20","Mon\u00e7\u00e3o","1604","Moreira Mnc","","42.0226","-8.4875","4"],"4950-609":["PT","4950-609","Moreira","Viana do Castelo","20","Mon\u00e7\u00e3o","1604","Moreira Mnc","","42.0226","-8.4875","4"],"4950-610":["PT","4950-610","Moreira","Viana do Castelo","20","Mon\u00e7\u00e3o","1604","Moreira Mnc","","42.0226","-8.4875","4"],"4950-611":["PT","4950-611","Moreira","Viana do Castelo","20","Mon\u00e7\u00e3o","1604","Moreira Mnc","","42.0226","-8.4875","4"],"4950-612":["PT","4950-612","Moreira","Viana do Castelo","20","Mon\u00e7\u00e3o","1604","Moreira Mnc","","42.0226","-8.4875","4"],"4950-613":["PT","4950-613","Moreira","Viana do Castelo","20","Mon\u00e7\u00e3o","1604","Moreira Mnc","","42.0226","-8.4875","4"],"4950-614":["PT","4950-614","Moreira","Viana do Castelo","20","Mon\u00e7\u00e3o","1604","Moreira Mnc","","42.0226","-8.4875","4"],"4950-615":["PT","4950-615","Moreira","Viana do Castelo","20","Mon\u00e7\u00e3o","1604","Moreira Mnc","","42.0226","-8.4875","4"],"4950-616":["PT","4950-616","Moreira","Viana do Castelo","20","Mon\u00e7\u00e3o","1604","Moreira Mnc","","42.0226","-8.4875","4"],"4950-617":["PT","4950-617","Moreira","Viana do Castelo","20","Mon\u00e7\u00e3o","1604","Moreira Mnc","","42.0226","-8.4875","4"],"4950-618":["PT","4950-618","Moreira","Viana do Castelo","20","Mon\u00e7\u00e3o","1604","Moreira Mnc","","42.0226","-8.4875","4"],"4950-619":["PT","4950-619","Moreira","Viana do Castelo","20","Mon\u00e7\u00e3o","1604","Moreira Mnc","","42.0226","-8.4875","4"],"4950-620":["PT","4950-620","Moreira","Viana do Castelo","20","Mon\u00e7\u00e3o","1604","Moreira Mnc","","42.0226","-8.4875","4"],"4950-621":["PT","4950-621","Moreira","Viana do Castelo","20","Mon\u00e7\u00e3o","1604","Moreira Mnc","","42.0226","-8.4875","4"],"4950-622":["PT","4950-622","Moreira","Viana do Castelo","20","Mon\u00e7\u00e3o","1604","Moreira Mnc","","42.0226","-8.4875","4"],"4950-623":["PT","4950-623","Moreira","Viana do Castelo","20","Mon\u00e7\u00e3o","1604","Moreira Mnc","","42.0226","-8.4875","4"],"4950-624":["PT","4950-624","Moreira","Viana do Castelo","20","Mon\u00e7\u00e3o","1604","Moreira Mnc","","42.0226","-8.4875","4"],"4950-625":["PT","4950-625","Moreira","Viana do Castelo","20","Mon\u00e7\u00e3o","1604","Moreira Mnc","","42.0226","-8.4875","4"],"4950-630":["PT","4950-630","Toleiro","Viana do Castelo","20","Mon\u00e7\u00e3o","1604","Parada Mnc","","42.0323","-8.4824","3"],"4950-640":["PT","4950-640","Retorta","Viana do Castelo","20","Mon\u00e7\u00e3o","1604","Pias Mnc","","41.9904","-8.4235","3"],"4950-641":["PT","4950-641","Alderiz","Viana do Castelo","20","Mon\u00e7\u00e3o","1604","Pias Mnc","","42.0272","-8.5159","4"],"4950-642":["PT","4950-642","Barreiro","Viana do Castelo","20","Mon\u00e7\u00e3o","1604","Pias Mnc","","42.018","-8.5068","4"],"4950-643":["PT","4950-643","Font\u00e3o","Viana do Castelo","20","Mon\u00e7\u00e3o","1604","Pias Mnc","","42.0129","-8.5096","4"],"4950-644":["PT","4950-644","Lamoso","Viana do Castelo","20","Mon\u00e7\u00e3o","1604","Pias Mnc","","42.015","-8.5139","4"],"4950-645":["PT","4950-645","Lapa","Viana do Castelo","20","Mon\u00e7\u00e3o","1604","Pias Mnc","","42.0095","-8.5002","4"],"4950-646":["PT","4950-646","Pias de Baixo","Viana do Castelo","20","Mon\u00e7\u00e3o","1604","Pias Mnc","","42.0043","-8.4651","1"],"4950-647":["PT","4950-647","Vila Nova","Viana do Castelo","20","Mon\u00e7\u00e3o","1604","Pias Mnc","","42.0294","-8.4976","4"],"4950-660":["PT","4950-660","Paus","Viana do Castelo","20","Mon\u00e7\u00e3o","1604","Pinheiros Mnc","","42.0404","-8.4989","3"],"4950-670":["PT","4950-670","Cachadinha","Viana do Castelo","20","Mon\u00e7\u00e3o","1604","Podame","","42.0048","-8.4583","3"],"4950-680":["PT","4950-680","Rio Bom","Viana do Castelo","20","Mon\u00e7\u00e3o","1604","Portela Mnc","","41.9903","-8.4718","4"],"4950-700":["PT","4950-700","Quintela","Viana do Castelo","20","Mon\u00e7\u00e3o","1604","Riba De Mouro","","41.9597","-8.4978","3"],"4950-701":["PT","4950-701","Aldeia","Viana do Castelo","20","Mon\u00e7\u00e3o","1604","Riba De Mouro","","42.0315","-8.3211","4"],"4950-702":["PT","4950-702","Bouco","Viana do Castelo","20","Mon\u00e7\u00e3o","1604","Riba De Mouro","","41.982","-8.4837","1"],"4950-703":["PT","4950-703","Carvalho","Viana do Castelo","20","Mon\u00e7\u00e3o","1604","Riba De Mouro","","41.982","-8.4837","1"],"4950-704":["PT","4950-704","Cavenca","Viana do Castelo","20","Mon\u00e7\u00e3o","1604","Riba De Mouro","","42.0289","-8.3096","4"],"4950-705":["PT","4950-705","Cordeiros","Viana do Castelo","20","Mon\u00e7\u00e3o","1604","Riba De Mouro","","41.982","-8.4837","1"],"4950-706":["PT","4950-706","Corga","Viana do Castelo","20","Mon\u00e7\u00e3o","1604","Riba De Mouro","","41.982","-8.4837","1"],"4950-707":["PT","4950-707","Costa","Viana do Castelo","20","Mon\u00e7\u00e3o","1604","Riba De Mouro","","42.0315","-8.3211","4"],"4950-708":["PT","4950-708","Cotaros","Viana do Castelo","20","Mon\u00e7\u00e3o","1604","Riba De Mouro","","41.982","-8.4837","1"],"4950-709":["PT","4950-709","Cruz Nova","Viana do Castelo","20","Mon\u00e7\u00e3o","1604","Riba De Mouro","","41.982","-8.4837","1"],"4950-710":["PT","4950-710","Cruzeiro","Viana do Castelo","20","Mon\u00e7\u00e3o","1604","Riba De Mouro","","42.0315","-8.3211","4"],"4950-711":["PT","4950-711","Freixo","Viana do Castelo","20","Mon\u00e7\u00e3o","1604","Riba De Mouro","","42.0315","-8.3211","1"],"4950-712":["PT","4950-712","Fundegos","Viana do Castelo","20","Mon\u00e7\u00e3o","1604","Riba De Mouro","","42.0257","-8.3377","4"],"4950-713":["PT","4950-713","Gateira","Viana do Castelo","20","Mon\u00e7\u00e3o","1604","Riba De Mouro","","42.0315","-8.3211","1"],"4950-714":["PT","4950-714","Lijo","Viana do Castelo","20","Mon\u00e7\u00e3o","1604","Riba De Mouro","","42.0426","-8.3096","4"],"4950-715":["PT","4950-715","Linhares","Viana do Castelo","20","Mon\u00e7\u00e3o","1604","Riba De Mouro","","42.0315","-8.3211","1"],"4950-716":["PT","4950-716","Pereiro","Viana do Castelo","20","Mon\u00e7\u00e3o","1604","Riba De Mouro","","42.0315","-8.3211","4"],"4950-717":["PT","4950-717","Portela","Viana do Castelo","20","Mon\u00e7\u00e3o","1604","Riba De Mouro","","42.0315","-8.3211","4"],"4950-718":["PT","4950-718","Quartas","Viana do Castelo","20","Mon\u00e7\u00e3o","1604","Riba De Mouro","","42.0321","-8.3281","4"],"4950-719":["PT","4950-719","Ribeiro","Viana do Castelo","20","Mon\u00e7\u00e3o","1604","Riba De Mouro","","42.0315","-8.3211","4"],"4950-720":["PT","4950-720","Rua","Viana do Castelo","20","Mon\u00e7\u00e3o","1604","Riba De Mouro","","41.9908","-8.4643","1"],"4950-721":["PT","4950-721","S\u00e3o Miguel","Viana do Castelo","20","Mon\u00e7\u00e3o","1604","Riba De Mouro","","41.9908","-8.4643","1"],"4950-740":["PT","4950-740","Real de Cima","Viana do Castelo","20","Mon\u00e7\u00e3o","1604","S\u00e1 Mnc","","41.931","-8.4286","3"],"4950-750":["PT","4950-750","Forno","Viana do Castelo","20","Mon\u00e7\u00e3o","1604","Sago","","42.0326","-8.4581","4"],"4950-760":["PT","4950-760","Igreja","Viana do Castelo","20","Mon\u00e7\u00e3o","1604","Segude","","42.0486","-8.3846","4"],"4950-761":["PT","4950-761","Terrada","Viana do Castelo","20","Mon\u00e7\u00e3o","1604","Segude","","42.0155","-8.3568","3"],"4950-762":["PT","4950-762","Crasto","Viana do Castelo","20","Mon\u00e7\u00e3o","1604","Segude","","42.0486","-8.3846","4"],"4950-770":["PT","4950-770","Vidro de Baixo","Viana do Castelo","20","Mon\u00e7\u00e3o","1604","Tangil","","41.9647","-8.535","3"],"4950-771":["PT","4950-771","Aldeia","Viana do Castelo","20","Mon\u00e7\u00e3o","1604","Tangil","","42.0128","-8.3443","4"],"4950-772":["PT","4950-772","Barronda","Viana do Castelo","20","Mon\u00e7\u00e3o","1604","Tangil","","41.9843","-8.5023","1"],"4950-773":["PT","4950-773","Cachada","Viana do Castelo","20","Mon\u00e7\u00e3o","1604","Tangil","","42.0128","-8.3443","4"],"4950-774":["PT","4950-774","Cotinho","Viana do Castelo","20","Mon\u00e7\u00e3o","1604","Tangil","","42.031","-8.3624","4"],"4950-775":["PT","4950-775","Coto","Viana do Castelo","20","Mon\u00e7\u00e3o","1604","Tangil","","42.0128","-8.3443","4"],"4950-776":["PT","4950-776","Crastelo","Viana do Castelo","20","Mon\u00e7\u00e3o","1604","Tangil","","41.9843","-8.5023","1"],"4950-777":["PT","4950-777","Cruzeiro","Viana do Castelo","20","Mon\u00e7\u00e3o","1604","Tangil","","42.0128","-8.3443","4"],"4950-778":["PT","4950-778","Fornelos","Viana do Castelo","20","Mon\u00e7\u00e3o","1604","Tangil","","42.0197","-8.3691","4"],"4950-779":["PT","4950-779","Igreja","Viana do Castelo","20","Mon\u00e7\u00e3o","1604","Tangil","","42.0128","-8.3443","4"],"4950-780":["PT","4950-780","Ladreda","Viana do Castelo","20","Mon\u00e7\u00e3o","1604","Tangil","","42.0273","-8.373","1"],"4950-781":["PT","4950-781","Lameira","Viana do Castelo","20","Mon\u00e7\u00e3o","1604","Tangil","","42.0235","-8.3547","4"],"4950-782":["PT","4950-782","Leiras","Viana do Castelo","20","Mon\u00e7\u00e3o","1604","Tangil","","42.0273","-8.373","1"],"4950-783":["PT","4950-783","Modelos","Viana do Castelo","20","Mon\u00e7\u00e3o","1604","Tangil","","42.0249","-8.3271","4"],"4950-784":["PT","4950-784","Pa\u00e7o","Viana do Castelo","20","Mon\u00e7\u00e3o","1604","Tangil","","42.0128","-8.3443","4"],"4950-785":["PT","4950-785","Pedral","Viana do Castelo","20","Mon\u00e7\u00e3o","1604","Tangil","","42.0273","-8.373","1"],"4950-786":["PT","4950-786","Santa Marinha","Viana do Castelo","20","Mon\u00e7\u00e3o","1604","Tangil","","42.0022","-8.3499","4"],"4950-787":["PT","4950-787","Trogal","Viana do Castelo","20","Mon\u00e7\u00e3o","1604","Tangil","","42.0284","-8.3645","4"],"4950-788":["PT","4950-788","Ventoso","Viana do Castelo","20","Mon\u00e7\u00e3o","1604","Tangil","","42.0273","-8.373","1"],"4950-789":["PT","4950-789","Vilar","Viana do Castelo","20","Mon\u00e7\u00e3o","1604","Tangil","","42.0128","-8.3443","4"],"4950-790":["PT","4950-790","Almas","Viana do Castelo","20","Mon\u00e7\u00e3o","1604","Tangil","","42.0128","-8.3443","1"],"4950-791":["PT","4950-791","Lisboa","Viana do Castelo","20","Mon\u00e7\u00e3o","1604","Tangil","","41.8733","-8.623","3"],"4950-800":["PT","4950-800","Troporiz","Viana do Castelo","20","Mon\u00e7\u00e3o","1604","Troporiz","","42.0575","-8.5205","4"],"4950-810":["PT","4950-810","Quinta da Sobreira","Viana do Castelo","20","Mon\u00e7\u00e3o","1604","Troviscoso","","41.9669","-8.4019","3"],"4950-811":["PT","4950-811","Bairro da Imaculada Concei\u00e7\u00e3o","Viana do Castelo","20","Mon\u00e7\u00e3o","1604","Troviscoso","","42.0066","-8.4559","1"],"4950-812":["PT","4950-812","Cristelo","Viana do Castelo","20","Mon\u00e7\u00e3o","1604","Troviscoso","","42.0703","-8.4582","4"],"4950-813":["PT","4950-813","Gandarela","Viana do Castelo","20","Mon\u00e7\u00e3o","1604","Troviscoso","","42.0724","-8.454","4"],"4950-814":["PT","4950-814","Igreja","Viana do Castelo","20","Mon\u00e7\u00e3o","1604","Troviscoso","","42.0703","-8.4582","4"],"4950-815":["PT","4950-815","Monte Redondo","Viana do Castelo","20","Mon\u00e7\u00e3o","1604","Troviscoso","","42.0703","-8.4582","4"],"4950-816":["PT","4950-816","Pedra","Viana do Castelo","20","Mon\u00e7\u00e3o","1604","Troviscoso","","42.061","-8.452","4"],"4950-817":["PT","4950-817","Reiriz","Viana do Castelo","20","Mon\u00e7\u00e3o","1604","Troviscoso","","42.0765","-8.4659","4"],"4950-818":["PT","4950-818","Ruivos","Viana do Castelo","20","Mon\u00e7\u00e3o","1604","Troviscoso","","42.0703","-8.4582","1"],"4950-819":["PT","4950-819","Senhora da Ajuda","Viana do Castelo","20","Mon\u00e7\u00e3o","1604","Troviscoso","","42.0703","-8.4582","1"],"4950-820":["PT","4950-820","Sobreira","Viana do Castelo","20","Mon\u00e7\u00e3o","1604","Troviscoso","","42.0294","-8.4976","1"],"4950-821":["PT","4950-821","Vila Nova","Viana do Castelo","20","Mon\u00e7\u00e3o","1604","Troviscoso","","42.0703","-8.4582","4"],"4950-830":["PT","4950-830","Outeiro","Viana do Castelo","20","Mon\u00e7\u00e3o","1604","Trute","","42.0083","-8.4687","4"],"4950-840":["PT","4950-840","Quinta da Ameosa","Viana do Castelo","20","Mon\u00e7\u00e3o","1604","Valadares Mnc","","42.0101","-8.4706","3"],"4950-850":["PT","4950-850","Bairro Alto","Viana do Castelo","20","Mon\u00e7\u00e3o","1604","Cortes","","42.0671","-8.4991","3"],"4950-851":["PT","4950-851","Cortes","Viana do Castelo","20","Mon\u00e7\u00e3o","1604","Cortes","","42.0725","-8.5136","4"],"4950-852":["PT","4950-852","Cortes","Viana do Castelo","20","Mon\u00e7\u00e3o","1604","Cortes","","42.0725","-8.5136","4"],"4950-853":["PT","4950-853","Eirado","Viana do Castelo","20","Mon\u00e7\u00e3o","1604","Cortes","","42.0716","-8.5101","4"],"4950-854":["PT","4950-854","Cortes","Viana do Castelo","20","Mon\u00e7\u00e3o","1604","Cortes","","42.0725","-8.5136","4"],"4950-855":["PT","4950-855","Cortes","Viana do Castelo","20","Mon\u00e7\u00e3o","1604","Cortes","","42.0725","-8.5136","4"],"4950-856":["PT","4950-856","Cortes","Viana do Castelo","20","Mon\u00e7\u00e3o","1604","Cortes","","42.0725","-8.5136","4"],"4950-857":["PT","4950-857","Cortes","Viana do Castelo","20","Mon\u00e7\u00e3o","1604","Cortes","","42.0725","-8.5136","4"],"4950-968":["PT","4950-968","Valinha","Viana do Castelo","20","Mon\u00e7\u00e3o","1604","Ceiv\u00e3es","","42.0681","-8.382","4"],"4950-969":["PT","4950-969","Mosteiro","Viana do Castelo","20","Mon\u00e7\u00e3o","1604","Merufe","","42.007","-8.3952","4"],"4950-997":["PT","4950-997","Cruzes","Viana do Castelo","20","Mon\u00e7\u00e3o","1604","Tangil","","42.0789","-8.4808","1"],"4950-999":["PT","4950-999","Mon\u00e7\u00e3o","Viana do Castelo","20","Mon\u00e7\u00e3o","1604","Mon\u00e7\u00e3o","","42.0789","-8.4808","4"]}